itkwasm_mesh_to_poly_data_emscripten/__init__.py
itkwasm_mesh_to_poly_data_emscripten/_version.py
itkwasm_mesh_to_poly_data_emscripten/js_package.py
itkwasm_mesh_to_poly_data_emscripten/mesh_to_poly_data_async.py
itkwasm_mesh_to_poly_data_emscripten/poly_data_to_mesh_async.py
itkwasm_mesh_to_poly_data_emscripten-1.1.1.dist-info/METADATA
itkwasm_mesh_to_poly_data_emscripten-1.1.1.dist-info/WHEEL
itkwasm_mesh_to_poly_data_emscripten-1.1.1.dist-info/RECORD
