Metadata-Version: 2.3
Name: itkwasm-mesh-to-poly-data-emscripten
Version: 1.1.1
Summary: Convert an ITK Mesh to a simple data structure compatible with vtkPolyData.
Project-URL: Home, https://github.com/InsightSoftwareConsortium/ITKMeshToPolyData
Project-URL: Source, https://github.com/InsightSoftwareConsortium/ITKMeshToPolyData
License-Expression: Apache-2.0
Keywords: emscripten,itkwasm,webassembly
Classifier: Development Status :: 3 - Alpha
Classifier: Environment :: WebAssembly
Classifier: Environment :: WebAssembly :: Emscripten
Classifier: Environment :: WebAssembly :: WASI
Classifier: Intended Audience :: Developers
Classifier: Intended Audience :: Science/Research
Classifier: License :: OSI Approved :: Apache Software License
Classifier: Programming Language :: C++
Classifier: Programming Language :: Python
Classifier: Programming Language :: Python :: 3
Classifier: Programming Language :: Python :: 3.8
Classifier: Programming Language :: Python :: 3.9
Classifier: Programming Language :: Python :: 3.10
Classifier: Programming Language :: Python :: 3.11
Classifier: Programming Language :: Python :: 3.12
Requires-Python: >=3.8
Requires-Dist: itkwasm>=1.0.b145
